drt_unet/__init__.py
drt_unet/train.py
drt_unet/unet.py
drt_unet/utils.py
drt_unet/models/checkpoint
drt_unet/models/modelbce_e2000_b16model.data-00000-of-00001
drt_unet/models/modelbce_e2000_b16model.index
drt_unet-0.0.9.dist-info/LICENSE
drt_unet-0.0.9.dist-info/METADATA
drt_unet-0.0.9.dist-info/WHEEL
drt_unet-0.0.9.dist-info/top_level.txt
drt_unet-0.0.9.dist-info/RECORD
