Metadata-Version: 2.1
Name: drt-unet
Version: 0.0.9
Summary: Neural network for mask creating
Home-page: https://github.com/dimiaa/drt-unet
Author: Dmitry Trokhachev
Author-email: dimiaa573@gmail.com
Project-URL: Bug Tracker, https://github.com/dimiaa/drt-unet/issues
Classifier: Programming Language :: Python :: 3
Classifier: License :: OSI Approved :: BSD License
Classifier: Operating System :: OS Independent
Requires-Python: >=3.6,<3.11
License-File: LICENSE
Requires-Dist: numpy
Requires-Dist: tensorflow
Requires-Dist: matplotlib
